mako_render/__init__.py
mako_render-0.1.0.dist-info/entry_points.txt
mako_render-0.1.0.dist-info/WHEEL
mako_render-0.1.0.dist-info/METADATA
mako_render-0.1.0.dist-info/RECORD
