Metadata-Version: 2.1
Name: mako-render
Version: 0.1.0
Summary: 
Author: gfreezy
Author-email: gfreezy@gmail.com
Requires-Python: >=3.7,<4.0
Classifier: Programming Language :: Python :: 3
Classifier: Programming Language :: Python :: 3.7
Requires-Dist: mako (>=1.1,<2.0)
